<?xml version="1.0" encoding="UTF-8"?>
 <resource xmlns="http://datacite.org/schema/kernel-4" xmlns:xsi="http://www.w3.org/2001/XMLSchema-instance" xsi:schemaLocation="http://datacite.org/schema/kernel-4 http://schema.datacite.org/meta/kernel-4/metadata.xsd">
	<identifier identifierType="DOI">10.1594/IEDA/100677</identifier>
	<creators>
		<creator>
			<creatorName>Hoagland,Beth</creatorName>
			<givenName>Beth</givenName>
			<familyName>Hoagland</familyName>
			<nameIdentifier nameIdentifierScheme="e-mail address">mailto:nell.hoagland@gmail.com</nameIdentifier>
			<nameIdentifier nameIdentifierScheme="grl person_num">urn:grl:person:1902</nameIdentifier>
		</creator>
		<creator>
			<creatorName>Wayman,Callum</creatorName>
			<givenName>Callum</givenName>
			<familyName>Wayman</familyName>
			<nameIdentifier nameIdentifierScheme="grl person_num">urn:grl:person:1911</nameIdentifier>
		</creator>
		<creator>
			<creatorName>Forsythe,Brandon</creatorName>
			<givenName>Brandon</givenName>
			<familyName>Forsythe</familyName>
			<nameIdentifier nameIdentifierScheme="grl person_num">urn:grl:person:1912</nameIdentifier>
		</creator>
		<creator>
			<creatorName>Russo,Tess</creatorName>
			<givenName>Tess</givenName>
			<familyName>Russo</familyName>
			<nameIdentifier nameIdentifierScheme="grl person_num">urn:grl:person:1913</nameIdentifier>
		</creator>
		<creator>
			<creatorName>Brantley,Susan L.</creatorName>
			<givenName>Susan L.</givenName>
			<familyName>Brantley</familyName>
			<nameIdentifier nameIdentifierScheme="grl person_num">urn:grl:person:1914</nameIdentifier>
		</creator>
	</creators>
	<titles>
		<title>Susquehanna Shale Hills Critical Zone Observatory - Shaver's Creek Watershed Stream Chemistry (2016)</title>
	</titles>
	<publisher>EarthChem Library(ECL) | Interdisciplinary Earth Data Alliance (IEDA) | Columbia University; doi:10.17616/R3V644</publisher>
	<publicationYear>2018</publicationYear>
	<resourceType resourceTypeGeneral="Dataset">Dataset</resourceType>
	<subjects>
		<subject subjectScheme="coverage scope">Regional (Continents, Oceans)</subject>
		<subject subjectScheme="IEDA Data Type">Chemistry:Fluid</subject>
		<subject subjectScheme="IEDA Feature of Interest">Critical Zone</subject>
		<subject subjectScheme="IEDA Topic">Geochemistry</subject>
		<subject subjectScheme="IEDA Topic">Near Surface Environment</subject>
		<subject subjectScheme="IEDA Topic">Solid Earth</subject>
		<subject subjectScheme="IEDA Topic">Terrestrial Hydrosphere</subject>
		<subject subjectScheme="constituent">DOC</subject>
		<subject subjectScheme="constituent">major ions</subject>
		<subject subjectScheme="place">Pennsylvania</subject>
		<subject subjectScheme="place">Shaver's Creek Watershed</subject>
		<subject subjectScheme="subject">Solute chemistry</subject>
	</subjects>
	<dates>
		<date dateType="Updated">metadata update:2017-04-19 10:51:56.23895</date>
		<date dateType="Available">2018-09-01</date>
		<date dateType="Created">2017-04-19T10:51:56.23895</date>
	</dates>
	<language>eng</language>
	<alternateIdentifiers>
		<alternateIdentifier alternateIdentifierType="IEDA submission_ID">urn:grl:submission:1058</alternateIdentifier>
		<alternateIdentifier alternateIdentifierType="URL">http://www.earthchem.org/library/browse/view?id=1058</alternateIdentifier>
	</alternateIdentifiers>
	<relatedIdentifiers/>
	<formats>
		<format>.xlsx  Microsoft Excel XML</format>
	</formats>
	<rightsList>
		<rights rightsURI="https://creativecommons.org/licenses/by-nc-sa/3.0/us/">Creative Commons Attribution-NonCommercial-Share Alike 3.0 United States [CC BY-NC-SA 3.0]</rights>
	</rightsList>
	<descriptions>
		<description descriptionType="Abstract">Chemistry for water samples collected from the Shaver's Creek Watershed are presented as part of Shale Hills Critical Zone Observatory research. Samples were collected from four sites along the mainstem of Shaver's Creek: above Lake Perez (SCAL), below Lake Perez (SCBL), at the agricultural site, Cole Farm (SCCF), and near the stream outlet (SCO). Additional spring and groundwater samples were collected from Cole Farm.  Grab samples were collected from the stream sites on a bi-weekly to monthly basis during 2016. Samples were processed for major cations, anions, and general physiochemical parameters as soon as possible following collection. This work was funded by NSF Critical Zone Observatory program grants to C. Duffy (EAR 07-25019) and S. L. Brantley (EAR 12-39285, EAR 13-31726). &#x0d;
		</description>
		<description descriptionType="Other">Related publications: </description>
	</descriptions>
	<geoLocations>
		<geoLocation>
			<geoLocationPlace>Shaver's Creek Watershed, Pennsylvania &#x0d;
			</geoLocationPlace>
			<geoLocationPoint>
				<pointLongitude>77.902569</pointLongitude>
				<pointLatitude>40.673619</pointLatitude>
			</geoLocationPoint>
		</geoLocation>
	</geoLocations>
</resource>